{"adult":false,"backdrop_path":"\/C8oE4pj9toWpP9L4G9CVCGr9VH.jpg","belongs_to_collection":{"id":441734,"name":"Horse Fever - Saga","poster_path":"\/b6qQCGIJm8L2dCswG2BZwZyUKsf.jpg","backdrop_path":"\/6mLnpZHBJWF5l6IRWFe7bN1L4hm.jpg"},"budget":0,"genres":[{"id":35,"name":"Com\u00e9die"}],"homepage":"","id":38528,"imdb_id":"tt0074520","origin_country":["IT"],"original_language":"it","original_title":"Febbre da cavallo","overview":"","popularity":0.7137000000000000010658141036401502788066864013671875,"poster_path":"\/zprLOtwwjjTF84YOGIZxakRu9Mc.jpg","production_companies":[{"id":5081,"logo_path":null,"name":"Primex","origin_country":"IT"}],"production_countries":[{"iso_3166_1":"IT","name":"Italy"}],"release_date":"1976-10-29","revenue":0,"runtime":90,"spoken_languages":[{"english_name":"Italian","iso_639_1":"it","name":"Italiano"}],"status":"Released","tagline":"","title":"Febbre da cavallo","video":false,"vote_average":7.29999999999999982236431605997495353221893310546875,"vote_count":365,"credits":{"cast":[{"adult":false,"gender":2,"id":109143,"known_for_department":"Acting","name":"Gigi Proietti","original_name":"Gigi Proietti","popularity":0.3951000000000000067501559897209517657756805419921875,"profile_path":"\/rgTazZ5DYTHBzARl3IyAAqpJrNL.jpg","cast_id":53,"character":"Bruno \"Mandrake\" Fioretti","credit_id":"63712250ca4f67009b551a94","order":0},{"adult":false,"gender":2,"id":21237,"known_for_department":"Acting","name":"Enrico Montesano","original_name":"Enrico Montesano","popularity":0.268100000000000004973799150320701301097869873046875,"profile_path":"\/myepIiCMGEwjhvZ3akFgVRogBP7.jpg","cast_id":54,"character":"Armando \"Er Pomata\" Pellicci","credit_id":"6371229c21621b00777de892","order":1},{"adult":false,"gender":1,"id":70119,"known_for_department":"Acting","name":"Catherine Spaak","original_name":"Catherine Spaak","popularity":0.68269999999999997353228309293626807630062103271484375,"profile_path":"\/5kiWPIlbNrpOCUxoDwrkKQLjqVJ.jpg","cast_id":55,"character":"Gabriella","credit_id":"637122b86bdec3007a430a9d","order":2},{"adult":false,"gender":2,"id":120637,"known_for_department":"Acting","name":"Mario Carotenuto","original_name":"Mario Carotenuto","popularity":0.38000000000000000444089209850062616169452667236328125,"profile_path":"\/xr7zoHY4fnmvn3ZwUoybvbSpdRG.jpg","cast_id":56,"character":"De Marchis","credit_id":"637122d121621b00cd631047","order":3},{"adult":false,"gender":2,"id":23370,"known_for_department":"Acting","name":"Francesco De Rosa","original_name":"Francesco De Rosa","popularity":0.152700000000000002398081733190338127315044403076171875,"profile_path":"\/25bERbOvvYvnXazFx37HFPE7OLP.jpg","cast_id":57,"character":"Felice Roversi","credit_id":"637122fa028420007d72c65d","order":4},{"adult":false,"gender":1,"id":36934,"known_for_department":"Acting","name":"Maria Teresa Albani","original_name":"Maria Teresa Albani","popularity":0.07220000000000000028865798640254070051014423370361328125,"profile_path":"\/uiac2SdVj446FrUJplwzXgsX5Ri.jpg","cast_id":58,"character":"Fortune-teller","credit_id":"6371231bd4a68b00cdca978f","order":5},{"adult":false,"gender":2,"id":32315,"known_for_department":"Acting","name":"Gigi Ballista","original_name":"Gigi Ballista","popularity":0.236300000000000010036416142611415125429630279541015625,"profile_path":"\/3WRolZCfz1KUJWiXScHcZakLbjl.jpg","cast_id":59,"character":"Count Dallara","credit_id":"6371232e798e0600dc368b67","order":6},{"adult":false,"gender":1,"id":101316,"known_for_department":"Acting","name":"Nikki Gentile","original_name":"Nikki Gentile","popularity":0.1605999999999999927613458794439793564379215240478515625,"profile_path":null,"cast_id":60,"character":"Mafalda","credit_id":"6371233fca4f67007fc33f76","order":7},{"adult":false,"gender":2,"id":9920,"known_for_department":"Acting","name":"Adolfo Celi","original_name":"Adolfo Celi","popularity":0.429900000000000004352074256530613638460636138916015625,"profile_path":"\/bIxjJ4eXYiNrYgSBCLD7OHw1LdT.jpg","cast_id":61,"character":"President of the Court","credit_id":"6371235602842000dcab4562","order":8},{"adult":false,"gender":2,"id":120027,"known_for_department":"Acting","name":"Ennio Antonelli","original_name":"Ennio Antonelli","popularity":0.343399999999999983035792183727608062326908111572265625,"profile_path":"\/k2BB0lgezdOHfkwarQkFGW4hY3U.jpg","cast_id":62,"character":"Otello \"Manzotin\" Rinaldi","credit_id":"63712378d4a68b00aa831db8","order":9},{"adult":false,"gender":2,"id":587455,"known_for_department":"Acting","name":"Luciano Bonanni","original_name":"Luciano Bonanni","popularity":0.2063000000000000111466391672365716658532619476318359375,"profile_path":"\/xhvUfngYYf4XAN5BC75rNN1MRD9.jpg","cast_id":63,"character":"Male Nurse","credit_id":"6371238bca4f6700bbbfff33","order":10},{"adult":false,"gender":2,"id":1455192,"known_for_department":"Acting","name":"Aristide Caporale","original_name":"Aristide Caporale","popularity":0.273500000000000020872192862952942959964275360107421875,"profile_path":"\/cddHzPjKY9LD7HCv7h9sykK1bQZ.jpg","cast_id":64,"character":"Augustarello","credit_id":"6371239ed4a68b00aa831dc0","order":11},{"adult":false,"gender":0,"id":1692859,"known_for_department":"Acting","name":"Gianfranco Cardinali","original_name":"Gianfranco Cardinali","popularity":0.00710000000000000040800696154974502860568463802337646484375,"profile_path":"\/kkeIHRzEqq6jyCSkBrTAwLIA2D.jpg","cast_id":65,"character":"Count Dallara's Assistant","credit_id":"637123b3d4a68b00910e7516","order":12},{"adult":false,"gender":2,"id":37125,"known_for_department":"Acting","name":"Giuseppe Castellano","original_name":"Giuseppe Castellano","popularity":0.1875999999999999889865875957184471189975738525390625,"profile_path":"\/sAy3jT3j6g6oFqvCeZbS8JWYIhd.jpg","cast_id":66,"character":"Stelvio Mazza","credit_id":"637123c86bdec3007a430aff","order":13},{"adult":false,"gender":2,"id":123911,"known_for_department":"Acting","name":"Fernando Cerulli","original_name":"Fernando Cerulli","popularity":0.260799999999999976285636194006656296551227569580078125,"profile_path":"\/1ndcO8hGmFDiS1gazT69TyzmJQv.jpg","cast_id":67,"character":"Commercial Director","credit_id":"637123e7ca4f67007fc33fba","order":14},{"adult":false,"gender":1,"id":269705,"known_for_department":"Acting","name":"Marina Confalone","original_name":"Marina Confalone","popularity":0.1761000000000000065281113847959204576909542083740234375,"profile_path":"\/zfT4a39HmaeN3rEVetEFFRxBXzI.jpg","cast_id":68,"character":"Giuliana Pellicci","credit_id":"637123fc6bdec3007a430b14","order":15},{"adult":false,"gender":1,"id":557347,"known_for_department":"Acting","name":"Nerina Montagnani","original_name":"Nerina Montagnani","popularity":0.1801000000000000100808250635964213870465755462646484375,"profile_path":"\/uiAvoQHQsOoejIXd3dMvMxp2gUC.jpg","cast_id":69,"character":"Er Pomata's Grandmother","credit_id":"6371240e6bdec3007d9f5b14","order":16},{"adult":false,"gender":0,"id":1855347,"known_for_department":"Acting","name":"Elena Magoia","original_name":"Elena Magoia","popularity":0.07929999999999999549249452002186444588005542755126953125,"profile_path":"\/hdlTH0oDGrHsHavGH4SplNPTcvq.jpg","cast_id":70,"character":"","credit_id":"637124481fa1c800cd859b6c","order":17},{"adult":false,"gender":2,"id":144617,"known_for_department":"Acting","name":"Renzo Ozzano","original_name":"Renzo Ozzano","popularity":0.203699999999999992184029906638897955417633056640625,"profile_path":"\/oYvPrWOoHFd1dGYbd509zm3Wp2b.jpg","cast_id":71,"character":"Jean-Louis Rossini","credit_id":"6371246621621b00777de927","order":18},{"adult":false,"gender":2,"id":1491992,"known_for_department":"Acting","name":"Fulvio Pellegrino","original_name":"Fulvio Pellegrino","popularity":0.0753999999999999948041562447542673908174037933349609375,"profile_path":"\/mMs72HBogmWTsST96OTuw1XZsrR.jpg","cast_id":72,"character":"Car Driver Fined by Mandrake","credit_id":"637124a6813831007730d996","order":19},{"adult":false,"gender":1,"id":1007633,"known_for_department":"Acting","name":"Marisa Traversi","original_name":"Marisa Traversi","popularity":0.1277999999999999969357844520345679484307765960693359375,"profile_path":"\/n4XsQQt0AWC9REke242DjvvuvYy.jpg","cast_id":73,"character":"De Marchis' Wife","credit_id":"637124c96bdec3007a430b6b","order":20},{"adult":false,"gender":2,"id":1692865,"known_for_department":"Acting","name":"Valentino Simeoni","original_name":"Valentino Simeoni","popularity":0.136500000000000010214051826551440171897411346435546875,"profile_path":"\/nHkG7CLwxmKuFcfup6geRhOEKfn.jpg","cast_id":74,"character":"Bleky","credit_id":"637124db6bdec3009be199cf","order":21},{"adult":false,"gender":0,"id":1137527,"known_for_department":"Acting","name":"Pietro Zardini","original_name":"Pietro Zardini","popularity":0.2039999999999999868993683094231528230011463165283203125,"profile_path":"\/vGyE1BFYvGIwZN17E5UxvwFkUBZ.jpg","cast_id":75,"character":"","credit_id":"637124ea1fa1c8007d3cc9b9","order":22},{"adult":false,"gender":0,"id":1885798,"known_for_department":"Acting","name":"Giancarlo Gregorini","original_name":"Giancarlo Gregorini","popularity":0.00710000000000000040800696154974502860568463802337646484375,"profile_path":null,"cast_id":76,"character":"Spartaco \"Er Ventresca\" (uncredited)","credit_id":"637125101684f700ab81640a","order":23},{"adult":false,"gender":2,"id":1174522,"known_for_department":"Acting","name":"Aldo Formisano","original_name":"Aldo Formisano","popularity":0.05960000000000000019984014443252817727625370025634765625,"profile_path":"\/6vSq7KqNtkKdq8lD3rgca8EwdTN.jpg","cast_id":77,"character":"Train Controller (uncredited)","credit_id":"6371252ae9c0dc00cd05894b","order":24},{"adult":false,"gender":0,"id":3784257,"known_for_department":"Acting","name":"Alberto Giubilo","original_name":"Alberto Giubilo","popularity":0.014300000000000000210942374678779742680490016937255859375,"profile_path":null,"cast_id":78,"character":"Horse Race Commentator (uncredited)","credit_id":"637125521fa1c8009b303a98","order":25},{"adult":false,"gender":2,"id":1599296,"known_for_department":"Acting","name":"Umberto Amambrini","original_name":"Umberto Amambrini","popularity":0.073099999999999998312461002569762058556079864501953125,"profile_path":"\/8OwPqXKslU5VGyCGeZ3oLm320HS.jpg","cast_id":79,"character":"Man in Betting Room (uncredited)","credit_id":"63712593798e06007fe62c49","order":26},{"adult":false,"gender":2,"id":1604920,"known_for_department":"Acting","name":"Antonio Spinnato","original_name":"Antonio Spinnato","popularity":0.09039999999999999424904473244168912060558795928955078125,"profile_path":"\/8ZM2yL5NKjhP0XsnTIcZ0TSvFFv.jpg","cast_id":80,"character":"Man in Betting Room (uncredited)","credit_id":"637125cdca4f67007fc34077","order":27},{"adult":false,"gender":2,"id":100941,"known_for_department":"Acting","name":"Giulio Massimini","original_name":"Giulio Massimini","popularity":0.295700000000000018385293287792592309415340423583984375,"profile_path":"\/7qArxsbLV04ogXll3fgblohEtyz.jpg","cast_id":81,"character":"Man in Betting Room (uncredited)","credit_id":"637125eed4a68b007fdad827","order":28},{"adult":false,"gender":2,"id":239655,"known_for_department":"Acting","name":"Giuseppe Marrocco","original_name":"Giuseppe Marrocco","popularity":0.20069999999999998951949464753852225840091705322265625,"profile_path":"\/tM6oJt72UIgOslnkIYTrBr0wLmi.jpg","cast_id":82,"character":"Man in Betting Room (uncredited)","credit_id":"6371262d81383100dd37097f","order":29},{"adult":false,"gender":1,"id":1452104,"known_for_department":"Acting","name":"Alba Maiolini","original_name":"Alba Maiolini","popularity":0.294999999999999984456877655247808434069156646728515625,"profile_path":"\/hqHkC2tdrifAFs2OaWkuPVpfVkj.jpg","cast_id":83,"character":"Woman in Betting Room (uncredited)","credit_id":"637126476bdec300ad2a6930","order":30},{"adult":false,"gender":0,"id":2019347,"known_for_department":"Acting","name":"Nancy Lecchini","original_name":"Nancy Lecchini","popularity":0.040399999999999998412381074786026147194206714630126953125,"profile_path":"\/kLhJqw25UerCdMC9Ag93lywxtEO.jpg","cast_id":84,"character":"Woman in Betting Room (uncredited)","credit_id":"6371265181383100dd37098a","order":31},{"adult":false,"gender":1,"id":1129103,"known_for_department":"Acting","name":"Eleonora Marchianti","original_name":"Eleonora Marchianti","popularity":0.0256000000000000012267964422107979771681129932403564453125,"profile_path":"\/dMzGyLtVEYI3aLuK3JXS1v4c6HX.jpg","cast_id":105,"character":"Woman in Betting Room (uncredited)","credit_id":"63714f5e1fa1c8009b304450","order":32},{"adult":false,"gender":2,"id":1140832,"known_for_department":"Acting","name":"Luciano Foti","original_name":"Luciano Foti","popularity":0.142600000000000004529709940470638684928417205810546875,"profile_path":"\/xFZXQmR42H2aE6DRnm0xnhnmSUF.jpg","cast_id":86,"character":"Count Dallara's Friend (uncredited)","credit_id":"6371272dd4a68b00910e764f","order":33},{"adult":false,"gender":0,"id":1688207,"known_for_department":"Acting","name":"Lanfranco Spinola","original_name":"Lanfranco Spinola","popularity":0.1545999999999999874322753612432279624044895172119140625,"profile_path":"\/paEwymUxgYBLvYBT4U5QGIyGNZR.jpg","cast_id":87,"character":"Count Dallara's Friend (uncredited)","credit_id":"63712738ca4f6700bbc00071","order":34},{"adult":false,"gender":0,"id":2190442,"known_for_department":"Acting","name":"Azzolino Carrega","original_name":"Azzolino Carrega","popularity":0.032699999999999999900079927783735911361873149871826171875,"profile_path":null,"cast_id":93,"character":"Count Dallara's Friend (uncredited)","credit_id":"637127c7d4a68b00aa831f0c","order":35},{"adult":false,"gender":1,"id":1706561,"known_for_department":"Acting","name":"Rossana Canghiari","original_name":"Rossana Canghiari","popularity":0.434099999999999985877963126768008805811405181884765625,"profile_path":"\/1EFFFDQnvt4wNzKLMQtHhDGl11a.jpg","cast_id":88,"character":"Fashion Model (uncredited)","credit_id":"637127631684f700c4eb55f0","order":36},{"adult":false,"gender":0,"id":2329675,"known_for_department":"Acting","name":"Mario Pascucci","original_name":"Mario Pascucci","popularity":0.07370000000000000162092561595272854901850223541259765625,"profile_path":"\/ymeUU28dZMrAXbon0ZFq30GiviL.jpg","cast_id":89,"character":"Associate Judge (uncredited)","credit_id":"6371277b798e0600b4d0aba3","order":37},{"adult":false,"gender":2,"id":1862469,"known_for_department":"Acting","name":"Vittorio Ripamonti","original_name":"Vittorio Ripamonti","popularity":0.04800000000000000099920072216264088638126850128173828125,"profile_path":"\/87r2YPDGiIeXrWuJEwpT6gR7ENb.jpg","cast_id":90,"character":"Associate Judge (uncredited)","credit_id":"6371278521621b00cd6311fe","order":38},{"adult":false,"gender":0,"id":2326057,"known_for_department":"Acting","name":"Giuseppe Namio","original_name":"Giuseppe Namio","popularity":0.033799999999999996713739847109536640346050262451171875,"profile_path":null,"cast_id":91,"character":"Trial Spectator (uncredited)","credit_id":"6371279b02842000b44ced9a","order":39},{"adult":false,"gender":2,"id":42847,"known_for_department":"Acting","name":"Aldo Valletti","original_name":"Aldo Valletti","popularity":0.26310000000000000053290705182007513940334320068359375,"profile_path":"\/dwNdnKCiZYGYSNI32SAWPt4GexN.jpg","cast_id":92,"character":"Trial Spectator (uncredited)","credit_id":"637127a321621b007dda2100","order":40},{"adult":false,"gender":2,"id":2201586,"known_for_department":"Acting","name":"Vezio Natili","original_name":"Vezio Natili","popularity":0.09239999999999999602540157184193958528339862823486328125,"profile_path":"\/tC7Ja8sWWq72ehe7hixCYLaGszj.jpg","cast_id":94,"character":"Trial Spectator (uncredited)","credit_id":"637127ffd4a68b00910e766a","order":41},{"adult":false,"gender":1,"id":1496297,"known_for_department":"Acting","name":"Lina Franchi","original_name":"Lina Franchi","popularity":0.1554999999999999993338661852249060757458209991455078125,"profile_path":null,"cast_id":95,"character":"Trial Spectator (uncredited)","credit_id":"6371281b81383100b51232ac","order":42},{"adult":false,"gender":0,"id":2093550,"known_for_department":"Acting","name":"Alvaro Tei","original_name":"Alvaro Tei","popularity":0.0738999999999999934718886152040795423090457916259765625,"profile_path":null,"cast_id":96,"character":"Trial Spectator (uncredited)","credit_id":"6371282e028420007a1c7bf0","order":43},{"adult":false,"gender":2,"id":25781,"known_for_department":"Acting","name":"Angelo Boscariol","original_name":"Angelo Boscariol","popularity":0.1711999999999999910738068820137414149940013885498046875,"profile_path":"\/uqZGaaoKv4t6d5olrT8JBHeIMZq.jpg","cast_id":97,"character":"Trial Spectator (uncredited)","credit_id":"637128496bdec300ad2a699a","order":44},{"adult":false,"gender":1,"id":239658,"known_for_department":"Acting","name":"Pupita Lea Scuderoni","original_name":"Pupita Lea Scuderoni","popularity":0.33779999999999998916422327965847216546535491943359375,"profile_path":"\/pxDyb9D194wt1GK4q1XLTcpUOal.jpg","cast_id":98,"character":"Trial Spectator (uncredited)","credit_id":"6371285c21621b00777dea7f","order":45},{"adult":false,"gender":1,"id":120114,"known_for_department":"Acting","name":"Franca Scagnetti","original_name":"Franca Scagnetti","popularity":0.340200000000000002398081733190338127315044403076171875,"profile_path":"\/xoCZ0leZ3jkahjjGehMus307nNP.jpg","cast_id":99,"character":"Train Passenger (uncredited)","credit_id":"637128741684f70080731a72","order":46},{"adult":false,"gender":2,"id":1684758,"known_for_department":"Acting","name":"Maurizio Streccioni","original_name":"Maurizio Streccioni","popularity":0.08279999999999999860111898897230275906622409820556640625,"profile_path":"\/e4FmxAtbbxGeR6WMmI3O2z1Qxza.jpg","cast_id":100,"character":"Airplane Passenger (uncredited)","credit_id":"637128841684f700ab8164db","order":47},{"adult":false,"gender":2,"id":1606424,"known_for_department":"Acting","name":"Luciano Zanussi","original_name":"Luciano Zanussi","popularity":0.193599999999999994315658113919198513031005859375,"profile_path":"\/gGeJtSS8qfp7ke50NN8yhswl9S.jpg","cast_id":101,"character":"Hippodrome Spectator (uncredited)","credit_id":"637128a2ca4f6700821202a3","order":48},{"adult":false,"gender":2,"id":1662214,"known_for_department":"Acting","name":"Mario Castaldi","original_name":"Mario Castaldi","popularity":0.07599999999999999811262085813723388127982616424560546875,"profile_path":"\/56r39kyEFwx8XXqE6uBU2a04VAJ.jpg","cast_id":102,"character":"Hippodrome Spectator (uncredited)","credit_id":"637128ab02842000b44cedcb","order":49},{"adult":false,"gender":2,"id":1019914,"known_for_department":"Acting","name":"Bruno Bertocci","original_name":"Bruno Bertocci","popularity":0.11709999999999999575894804593190201558172702789306640625,"profile_path":"\/bDp2SQcGSkQ0jclMZSyHaqpjwul.jpg","cast_id":104,"character":"Tribunal Guard (uncredited)","credit_id":"63712912e9c0dc00b488a738","order":50},{"adult":false,"gender":0,"id":5188758,"known_for_department":"Acting","name":"Domenico Demitri","original_name":"Domenico Demitri","popularity":0.0256000000000000012267964422107979771681129932403564453125,"profile_path":"\/pHugHIYfzdSbu5pQfjb9GlpfUsu.jpg","cast_id":106,"character":"Commercial Actor (uncredited)","credit_id":"678c4e89dbcff33a9c650784","order":51},{"adult":false,"gender":0,"id":4551327,"known_for_department":"Acting","name":"Sergio Silveri","original_name":"Sergio Silveri","popularity":0.0213999999999999988842258602517176768742501735687255859375,"profile_path":"\/1ru2Rgvgi6vrnmDdR3jDZI1L9t6.jpg","cast_id":107,"character":"(uncredited)","credit_id":"678ddbb47c7047471b433e05","order":52}],"crew":[{"adult":false,"gender":2,"id":67924,"known_for_department":"Directing","name":"Steno","original_name":"Steno","popularity":0.5646999999999999797495320308371447026729583740234375,"profile_path":"\/osXoJ0ARTKcpGiQ8WuZ0jm0STPA.jpg","credit_id":"52fe46c39251416c9105edf7","department":"Directing","job":"Director"},{"adult":false,"gender":2,"id":264596,"known_for_department":"Production","name":"Roberto Infascelli","original_name":"Roberto Infascelli","popularity":0.1229999999999999982236431605997495353221893310546875,"profile_path":null,"credit_id":"62f29c671511aa007a7d0e78","department":"Production","job":"Producer"},{"adult":false,"gender":2,"id":67924,"known_for_department":"Directing","name":"Steno","original_name":"Steno","popularity":0.5646999999999999797495320308371447026729583740234375,"profile_path":"\/osXoJ0ARTKcpGiQ8WuZ0jm0STPA.jpg","credit_id":"62f29cd65b2f47007ffaeaf3","department":"Writing","job":"Screenplay"},{"adult":false,"gender":0,"id":1606262,"known_for_department":"Production","name":"Lucio Orlandini","original_name":"Lucio Orlandini","popularity":0.04370000000000000273114864057788508944213390350341796875,"profile_path":null,"credit_id":"62f29cf4fea6e3007d077d8a","department":"Production","job":"Production Manager"},{"adult":false,"gender":0,"id":2357724,"known_for_department":"Production","name":"Egidio Valentini","original_name":"Egidio Valentini","popularity":0.0995000000000000051070259132757200859487056732177734375,"profile_path":null,"credit_id":"62f29cfccee2f6007a8e37d1","department":"Production","job":"Unit Manager"},{"adult":false,"gender":0,"id":102632,"known_for_department":"Art","name":"Franco Bottari","original_name":"Franco Bottari","popularity":0.1464999999999999913402604079237789846956729888916015625,"profile_path":null,"credit_id":"62f29d0ce72fe800822db2af","department":"Art","job":"Production Design"},{"adult":false,"gender":0,"id":1003920,"known_for_department":"Costume & Make-Up","name":"Bruna Parmesan","original_name":"Bruna Parmesan","popularity":0.100800000000000000710542735760100185871124267578125,"profile_path":null,"credit_id":"62f29d20db72c00091a48b78","department":"Costume & Make-Up","job":"Costume Design"},{"adult":false,"gender":0,"id":1946547,"known_for_department":"Camera","name":"Emilio Loffredo","original_name":"Emilio Loffredo","popularity":0.02809999999999999997779553950749686919152736663818359375,"profile_path":null,"credit_id":"62f29d425b2f47007ffaeb19","department":"Camera","job":"Director of Photography"},{"adult":false,"gender":2,"id":69065,"known_for_department":"Editing","name":"Raimondo Crociani","original_name":"Raimondo Crociani","popularity":0.12609999999999998987476601541857235133647918701171875,"profile_path":"\/7LdNFW07NIWGvEXfhD5DAeRYm5W.jpg","credit_id":"62f29d5b880c9200828f66b2","department":"Editing","job":"Editor"},{"adult":false,"gender":2,"id":72678,"known_for_department":"Sound","name":"Franco Bixio","original_name":"Franco Bixio","popularity":0.0461000000000000020872192862952942959964275360107421875,"profile_path":null,"credit_id":"62f29d6f5be00e007ad98b50","department":"Sound","job":"Original Music Composer"},{"adult":false,"gender":2,"id":59366,"known_for_department":"Sound","name":"Fabio Frizzi","original_name":"Fabio Frizzi","popularity":0.16630000000000000337507799486047588288784027099609375,"profile_path":"\/oern7qrqjQsvP9WU7Gg66QMP3KT.jpg","credit_id":"62f29d7adb72c0007a062be6","department":"Sound","job":"Original Music Composer"},{"adult":false,"gender":2,"id":72679,"known_for_department":"Sound","name":"Vince Tempera","original_name":"Vince Tempera","popularity":0.08770000000000000017763568394002504646778106689453125,"profile_path":"\/iK3OK5l1KfZyIMBMfrPc4cl5WJC.jpg","credit_id":"62f29d8523be460091e89cdc","department":"Sound","job":"Original Music Composer"},{"adult":false,"gender":0,"id":3657334,"known_for_department":"Sound","name":"Renato Checcacci","original_name":"Renato Checcacci","popularity":0.00710000000000000040800696154974502860568463802337646484375,"profile_path":null,"credit_id":"62f29dfe5b2f47007ffaeb53","department":"Sound","job":"Boom Operator"},{"adult":false,"gender":2,"id":220970,"known_for_department":"Directing","name":"Lodovico Gasparini","original_name":"Lodovico Gasparini","popularity":0.2436000000000000109690034832965466193854808807373046875,"profile_path":"\/xIpGAzYT2YHdZ1MsPUAtCNI6U9z.jpg","credit_id":"62f29e0b1511aa007d42afa6","department":"Directing","job":"First Assistant Director"},{"adult":false,"gender":1,"id":1612806,"known_for_department":"Directing","name":"Vittoria Vigorelli","original_name":"Vittoria Vigorelli","popularity":0.1645999999999999963140595582444802857935428619384765625,"profile_path":null,"credit_id":"62f29e25514c4a007f8c1a0a","department":"Directing","job":"Script Supervisor"},{"adult":false,"gender":0,"id":3438829,"known_for_department":"Production","name":"Paolo Bistolfi","original_name":"Paolo Bistolfi","popularity":0.00710000000000000040800696154974502860568463802337646484375,"profile_path":null,"credit_id":"62f29e33594c940082cfac7c","department":"Production","job":"Production Secretary"},{"adult":false,"gender":2,"id":20844,"known_for_department":"Camera","name":"Giovanni Fiore Coltellacci","original_name":"Giovanni Fiore Coltellacci","popularity":0.1756999999999999950706097706643049605190753936767578125,"profile_path":null,"credit_id":"62f29e4923be46007dbb8395","department":"Camera","job":"Camera Operator"},{"adult":false,"gender":0,"id":1539815,"known_for_department":"Camera","name":"Sandro Rubbo","original_name":"Sandro Rubbo","popularity":0.0310999999999999991728838466542583773843944072723388671875,"profile_path":null,"credit_id":"62f29e685b2f47007a760e21","department":"Camera","job":"Assistant Camera"},{"adult":false,"gender":0,"id":1734424,"known_for_department":"Camera","name":"Pino Venditti","original_name":"Pino Venditti","popularity":0.0261000000000000016708856520608605933375656604766845703125,"profile_path":null,"credit_id":"62f29e77514c4a008291fb10","department":"Camera","job":"Assistant Camera"},{"adult":true,"gender":0,"id":1632425,"known_for_department":"Camera","name":"Giuseppina di Cola","original_name":"Giuseppina di Cola","popularity":0.59999999999999997779553950749686919152736663818359375,"profile_path":null,"credit_id":"62f29e93880c9200828f66e9","department":"Camera","job":"Still Photographer"},{"adult":false,"gender":0,"id":1712461,"known_for_department":"Sound","name":"Giorgio Pallotta","original_name":"Giorgio Pallotta","popularity":0.050999999999999996724842077355788205750286579132080078125,"profile_path":null,"credit_id":"62f29eb35b2f47007a760e3a","department":"Sound","job":"Sound"},{"adult":false,"gender":0,"id":2340273,"known_for_department":"Sound","name":"Manlio Urbani","original_name":"Manlio Urbani","popularity":0.050999999999999996724842077355788205750286579132080078125,"profile_path":null,"credit_id":"62f29ebb41ad8d0082412779","department":"Sound","job":"Boom Operator"},{"adult":false,"gender":0,"id":1606290,"known_for_department":"Costume & Make-Up","name":"Gloria Granati","original_name":"Gloria Granati","popularity":0.07920000000000000650590692430341732688248157501220703125,"profile_path":null,"credit_id":"62f29ec61511aa007a7d0eed","department":"Costume & Make-Up","job":"Makeup Artist"},{"adult":false,"gender":0,"id":1625595,"known_for_department":"Costume & Make-Up","name":"Vittoria Silvi","original_name":"Vittoria Silvi","popularity":0.052999999999999998501198916756038670428097248077392578125,"profile_path":null,"credit_id":"62f29ed11f748b007cc9825d","department":"Costume & Make-Up","job":"Hairstylist"},{"adult":false,"gender":0,"id":1547576,"known_for_department":"Art","name":"Mauro Passi","original_name":"Mauro Passi","popularity":0.082100000000000006306066779870889149606227874755859375,"profile_path":null,"credit_id":"62f29edc1f748b0081169090","department":"Art","job":"Assistant Production Design"},{"adult":false,"gender":2,"id":1158334,"known_for_department":"Editing","name":"Francesco Malvestito","original_name":"Francesco Malvestito","popularity":0.041799999999999996880273300803310121409595012664794921875,"profile_path":null,"credit_id":"62f29f1afea6e30091355e27","department":"Editing","job":"Assistant Editor"},{"adult":false,"gender":0,"id":1708372,"known_for_department":"Editing","name":"Adelchi Marinangeli","original_name":"Adelchi Marinangeli","popularity":0.06590000000000000024424906541753443889319896697998046875,"profile_path":null,"credit_id":"62f29f31cee2f600829633a9","department":"Editing","job":"Assistant Editor"},{"adult":false,"gender":0,"id":1707532,"known_for_department":"Editing","name":"Mariella Scalese","original_name":"Mariella Scalese","popularity":0.0167999999999999989619414719754786347039043903350830078125,"profile_path":null,"credit_id":"62f29f3a5be00e007ad98baa","department":"Editing","job":"Assistant Editor"},{"adult":false,"gender":0,"id":938562,"known_for_department":"Writing","name":"Massimo Patrizi","original_name":"Massimo Patrizi","popularity":0.171899999999999997246646898929611779749393463134765625,"profile_path":null,"credit_id":"5c3db5189251416e06ad662e","department":"Writing","job":"Story"},{"adult":false,"gender":2,"id":938721,"known_for_department":"Writing","name":"Alfredo Giannetti","original_name":"Alfredo Giannetti","popularity":0.203199999999999991739940696788835339248180389404296875,"profile_path":null,"credit_id":"5c3db5299251416b02ad861e","department":"Writing","job":"Screenplay"},{"adult":false,"gender":2,"id":69040,"known_for_department":"Writing","name":"Enrico Vanzina","original_name":"Enrico Vanzina","popularity":0.209199999999999997069011214989586733281612396240234375,"profile_path":"\/Abmy1bcaHoBrQCUcOh60QE9tJiF.jpg","credit_id":"5c3db532c3a36821623e590d","department":"Writing","job":"Screenplay"}]}}