{"adult":false,"backdrop_path":"\/55hRgXkbvHoc9dL58S9HAGyxmZt.jpg","belongs_to_collection":{"id":1254578,"name":"\u0e15\u0e33\u0e19\u0e32\u0e19 \"\u0e18\u0e35\u0e48\u0e2b\u0e22\u0e14\"","poster_path":"\/fQJnhV6xds9py3SFIUMR3RxUWrp.jpg","backdrop_path":"\/i419ZnsQgpAia5g9K42vVqWqg77.jpg"},"budget":0,"genres":[{"id":27,"name":"Horreur"},{"id":53,"name":"Thriller"}],"homepage":"","id":1134433,"imdb_id":"tt29609422","origin_country":["TH"],"original_language":"th","original_title":"\u0e18\u0e35\u0e48\u0e2b\u0e22\u0e14","overview":"Lorsqu'un esprit assoiff\u00e9 de sang poss\u00e8de une jeune fille dans un village isol\u00e9, son fr\u00e8re a\u00een\u00e9 se charge de le bannir avant qu'elle ne soit consum\u00e9e par le mal.","popularity":4.3087999999999997413624441833235323429107666015625,"poster_path":"\/wmenjROhs4AI4vDBmSVy3d1tLL7.jpg","production_companies":[{"id":150189,"logo_path":null,"name":"Minds@Work","origin_country":""},{"id":7924,"logo_path":"\/1KG5lcXO8GZ2F6SshuMYw1Yf4vX.png","name":"M Studio","origin_country":"TH"}],"production_countries":[{"iso_3166_1":"TH","name":"Thailand"}],"release_date":"2023-10-25","revenue":15150000,"runtime":121,"spoken_languages":[{"english_name":"Thai","iso_639_1":"th","name":"\u0e20\u0e32\u0e29\u0e32\u0e44\u0e17\u0e22"}],"status":"Released","tagline":"","title":"Death Whisperer","video":false,"vote_average":7.5,"vote_count":200,"credits":{"cast":[{"adult":false,"gender":2,"id":1197012,"known_for_department":"Acting","name":"\u0e13\u0e40\u0e14\u0e0a\u0e19\u0e4c \u0e04\u0e39\u0e01\u0e34\u0e21\u0e34\u0e22\u0e30","original_name":"\u0e13\u0e40\u0e14\u0e0a\u0e19\u0e4c \u0e04\u0e39\u0e01\u0e34\u0e21\u0e34\u0e22\u0e30","popularity":1.5524999999999999911182158029987476766109466552734375,"profile_path":"\/w58HrktpHZ7UVGY5SKoJxFkitCy.jpg","cast_id":1,"character":"Yak","credit_id":"64c00903be6d8800ae17a198","order":0},{"adult":false,"gender":2,"id":3415057,"known_for_department":"Acting","name":"\u0e01\u0e32\u0e08\u0e1a\u0e31\u0e13\u0e11\u0e34\u0e15 \u0e43\u0e08\u0e14\u0e35","original_name":"\u0e01\u0e32\u0e08\u0e1a\u0e31\u0e13\u0e11\u0e34\u0e15 \u0e43\u0e08\u0e14\u0e35","popularity":0.580200000000000049027448767446912825107574462890625,"profile_path":"\/4XCjfePa5LYyYoUjWfwsODxszT0.jpg","cast_id":3,"character":"Yos","credit_id":"64c009ca0582240151f3ab25","order":1},{"adult":false,"gender":2,"id":4338889,"known_for_department":"Acting","name":"\u0e1e\u0e35\u0e23\u0e30\u0e01\u0e24\u0e15\u0e22\u0e4c \u0e1e\u0e0a\u0e23\u0e1a\u0e38\u0e13\u0e22\u0e40\u0e01\u0e35\u0e22\u0e23\u0e15\u0e34","original_name":"\u0e1e\u0e35\u0e23\u0e30\u0e01\u0e24\u0e15\u0e22\u0e4c \u0e1e\u0e0a\u0e23\u0e1a\u0e38\u0e13\u0e22\u0e40\u0e01\u0e35\u0e22\u0e23\u0e15\u0e34","popularity":0.5324999999999999733546474089962430298328399658203125,"profile_path":"\/tr7Lmmqp1iRKlSaoJCyec0OZ1sf.jpg","cast_id":11,"character":"Yod","credit_id":"65392616f495ee013ae1d050","order":2},{"adult":false,"gender":1,"id":3947368,"known_for_department":"Acting","name":"\u0e40\u0e08\u0e25\u0e35\u0e25\u0e0a\u0e32 \u0e04\u0e31\u0e1b\u0e1b\u0e38\u0e19","original_name":"\u0e40\u0e08\u0e25\u0e35\u0e25\u0e0a\u0e32 \u0e04\u0e31\u0e1b\u0e1b\u0e38\u0e19","popularity":0.57609999999999994546584503041231073439121246337890625,"profile_path":"\/d7rfzM7mmsHNKor8dXJ2f81I9qR.jpg","cast_id":2,"character":"Yad","credit_id":"64c0093f8ee49c0fce45dcf7","order":3},{"adult":false,"gender":1,"id":4338888,"known_for_department":"Acting","name":"\u0e23\u0e31\u0e15\u0e19\u0e27\u0e14\u0e35 \u0e27\u0e07\u0e28\u0e4c\u0e17\u0e2d\u0e07","original_name":"\u0e23\u0e31\u0e15\u0e19\u0e27\u0e14\u0e35 \u0e27\u0e07\u0e28\u0e4c\u0e17\u0e2d\u0e07","popularity":1.3635999999999999232613845379091799259185791015625,"profile_path":"\/cF5AWXXOleumTIEIp4DRFri9RxF.jpg","cast_id":10,"character":"Yam","credit_id":"653925e1c50ad200ad5ad09f","order":4},{"adult":false,"gender":1,"id":3606315,"known_for_department":"Acting","name":"\u0e13\u0e31\u0e10\u0e0a\u0e32 \u0e1e\u0e32\u0e42\u0e14\u0e27\u0e31\u0e19","original_name":"\u0e13\u0e31\u0e10\u0e0a\u0e32 \u0e1e\u0e32\u0e42\u0e14\u0e27\u0e31\u0e19","popularity":0.576200000000000045474735088646411895751953125,"profile_path":"\/3xvUSnerABXxlaX4x1bTDhlMvt3.jpg","cast_id":9,"character":"Yee","credit_id":"65392575f495ee00e2c58d6d","order":5},{"adult":false,"gender":2,"id":1027750,"known_for_department":"Acting","name":"\u0e1b\u0e23\u0e40\u0e21\u0e28\u0e23\u0e4c \u0e19\u0e49\u0e2d\u0e22\u0e2d\u0e48\u0e33","original_name":"\u0e1b\u0e23\u0e40\u0e21\u0e28\u0e23\u0e4c \u0e19\u0e49\u0e2d\u0e22\u0e2d\u0e48\u0e33","popularity":0.67479999999999995541344333105371333658695220947265625,"profile_path":"\/8qu82ac9tKjRGBHlCoKZRT864TT.jpg","cast_id":5,"character":"Hang","credit_id":"64c00b296d4c97011cba46f2","order":6},{"adult":false,"gender":1,"id":1203876,"known_for_department":"Acting","name":"\u0e2d\u0e23\u0e34\u0e28\u0e23\u0e32 \u0e27\u0e07\u0e29\u0e4c\u0e0a\u0e32\u0e25\u0e35","original_name":"\u0e2d\u0e23\u0e34\u0e28\u0e23\u0e32 \u0e27\u0e07\u0e29\u0e4c\u0e0a\u0e32\u0e25\u0e35","popularity":0.94869999999999998774313780813827179372310638427734375,"profile_path":"\/p8KgolBImhMDs12qjzYiuYo9iUM.jpg","cast_id":4,"character":"Boonyen","credit_id":"64c00afd05822400eed83805","order":7},{"adult":false,"gender":2,"id":1560844,"known_for_department":"Acting","name":"\u0e2d\u0e07\u0e2d\u0e32\u0e08 \u0e40\u0e08\u0e35\u0e22\u0e21\u0e40\u0e08\u0e23\u0e34\u0e0d\u0e1e\u0e23\u0e01\u0e38\u0e25","original_name":"\u0e2d\u0e07\u0e2d\u0e32\u0e08 \u0e40\u0e08\u0e35\u0e22\u0e21\u0e40\u0e08\u0e23\u0e34\u0e0d\u0e1e\u0e23\u0e01\u0e38\u0e25","popularity":0.6755999999999999783284465593169443309307098388671875,"profile_path":"\/i3e4IuDngcByoViRZ8HMwNMNdRw.jpg","cast_id":15,"character":"Sergeant Paphan","credit_id":"653be9cfbc2cb3012c30a5a5","order":8},{"adult":false,"gender":2,"id":1691923,"known_for_department":"Acting","name":"Porjed Kaenpetch","original_name":"Porjed Kaenpetch","popularity":0.059999999999999997779553950749686919152736663818359375,"profile_path":"\/bfd8lfExflqMM7P2E5ks7fYm5JV.jpg","cast_id":32,"character":"Mr. Puth","credit_id":"6618f516e4c9eb017c2ad39c","order":9},{"adult":false,"gender":1,"id":3638742,"known_for_department":"Acting","name":"Manita Chobchuen","original_name":"Manita Chobchuen","popularity":0.0909999999999999975575093458246556110680103302001953125,"profile_path":"\/qm4r0udVT5dZzaHbu0fiqB7M3Vs.jpg","cast_id":17,"character":"Black Spirit","credit_id":"6618ef44b9a0bd017c115d33","order":10},{"adult":false,"gender":0,"id":4598577,"known_for_department":"Acting","name":"Jampar Saenprom","original_name":"Jampar Saenprom","popularity":0.1287999999999999978239628717346931807696819305419921875,"profile_path":null,"cast_id":16,"character":"Chuay","credit_id":"65f6c631903c52017e285636","order":11},{"adult":false,"gender":1,"id":4648868,"known_for_department":"Acting","name":"Samiha Lamloet Haque","original_name":"Samiha Lamloet Haque","popularity":0.0256000000000000012267964422107979771681129932403564453125,"profile_path":"\/ovceKPrnqk1JHP8tuWueifO3B89.jpg","cast_id":18,"character":"Nart","credit_id":"6618f005109cd0017ea3827b","order":12},{"adult":false,"gender":2,"id":2114696,"known_for_department":"Acting","name":"Peerapol Kijreunpiromsuk","original_name":"Peerapol Kijreunpiromsuk","popularity":0.038899999999999997080113445235838298685848712921142578125,"profile_path":"\/iL7cJ4Vn8WfGJLUwOpBY1RLxZ0r.jpg","cast_id":19,"character":"Ming","credit_id":"6618f030e10f46017db549c0","order":13},{"adult":false,"gender":1,"id":3115102,"known_for_department":"Acting","name":"\u0e19\u0e31\u0e14\u0e14\u0e32 \u0e0a\u0e27\u0e27\u0e32\u0e19\u0e34\u0e0a","original_name":"\u0e19\u0e31\u0e14\u0e14\u0e32 \u0e0a\u0e27\u0e27\u0e32\u0e19\u0e34\u0e0a","popularity":0.175499999999999989341858963598497211933135986328125,"profile_path":null,"cast_id":20,"character":"Nee","credit_id":"6618f067af3da60163186845","order":14},{"adult":false,"gender":2,"id":3226034,"known_for_department":"Acting","name":"Sorabodee Changsiri","original_name":"Sorabodee Changsiri","popularity":0.08200000000000000344169137633798527531325817108154296875,"profile_path":null,"cast_id":21,"character":"Mun","credit_id":"6618f2104da3d4016291a592","order":15},{"adult":false,"gender":0,"id":4648877,"known_for_department":"Acting","name":"Panida Sararat","original_name":"Panida Sararat","popularity":0.050599999999999999145128271038629463873803615570068359375,"profile_path":null,"cast_id":22,"character":"Girl Student","credit_id":"6618f23ae4c9eb017c2ad105","order":16},{"adult":false,"gender":0,"id":4648879,"known_for_department":"Acting","name":"Autthawikorn Tookaew","original_name":"Autthawikorn Tookaew","popularity":0.032699999999999999900079927783735911361873149871826171875,"profile_path":null,"cast_id":23,"character":"Boy Student","credit_id":"6618f26c3acd20017c46ca6e","order":17},{"adult":false,"gender":0,"id":4648880,"known_for_department":"Acting","name":"Phitchayapha Salaesakul","original_name":"Phitchayapha Salaesakul","popularity":0.0213999999999999988842258602517176768742501735687255859375,"profile_path":null,"cast_id":24,"character":"Roadside Ghost","credit_id":"6618f2b73acd20017c46cad8","order":18},{"adult":false,"gender":0,"id":4648881,"known_for_department":"Acting","name":"Kunyapak Noppawong Na Ayutthya","original_name":"Kunyapak Noppawong Na Ayutthya","popularity":0.0239000000000000011046719095020307577215135097503662109375,"profile_path":null,"cast_id":25,"character":"Roadside Ghost","credit_id":"6618f2ecbbcae0016294fd9d","order":19},{"adult":false,"gender":1,"id":3231578,"known_for_department":"Acting","name":"Neennara Boonnithipaisit","original_name":"Neennara Boonnithipaisit","popularity":0.1731000000000000038635761256955447606742382049560546875,"profile_path":"\/hsS7lnO9Upj0HPdGKXl5wO1IVRd.jpg","cast_id":26,"character":"Floating Ghost","credit_id":"6618f31ce0ec5101634a153e","order":20},{"adult":false,"gender":0,"id":4648882,"known_for_department":"Acting","name":"Aitsaranuchat Homhuan","original_name":"Aitsaranuchat Homhuan","popularity":0.0213999999999999988842258602517176768742501735687255859375,"profile_path":null,"cast_id":27,"character":"Floating Ghost","credit_id":"6618f34ce10f46017db54c15","order":21},{"adult":false,"gender":0,"id":4648884,"known_for_department":"Acting","name":"Jiranya Pakhiao","original_name":"Jiranya Pakhiao","popularity":0.02860000000000000042188474935755948536098003387451171875,"profile_path":null,"cast_id":28,"character":"Floating Ghost","credit_id":"6618f378e4c9eb017c2ad299","order":22},{"adult":false,"gender":0,"id":4648885,"known_for_department":"Acting","name":"Sasipa Sedboobpa","original_name":"Sasipa Sedboobpa","popularity":0.045699999999999997568611576070907176472246646881103515625,"profile_path":null,"cast_id":29,"character":"Floating Ghost","credit_id":"6618f3b190cf51017ca21f56","order":23},{"adult":false,"gender":0,"id":4648887,"known_for_department":"Acting","name":"Suriwipa Yimlamai","original_name":"Suriwipa Yimlamai","popularity":0.05380000000000000059952043329758453182876110076904296875,"profile_path":null,"cast_id":30,"character":"Floating Ghost","credit_id":"6618f3dcbbcae0016294fe7e","order":24},{"adult":false,"gender":0,"id":4648889,"known_for_department":"Acting","name":"Warinthorn Phupakrae","original_name":"Warinthorn Phupakrae","popularity":0.03819999999999999784616733222719631157815456390380859375,"profile_path":null,"cast_id":31,"character":"Floating Ghost","credit_id":"6618f4242b2108017dba374a","order":25}],"crew":[{"adult":false,"gender":2,"id":146515,"known_for_department":"Directing","name":"Taweewat Wantha","original_name":"Taweewat Wantha","popularity":0.2492999999999999938271599830841296352446079254150390625,"profile_path":"\/2uel0thVqnfxWFVoRhcG4t9hhqM.jpg","credit_id":"650beae9b5bc21014e90c8a5","department":"Directing","job":"Director"},{"adult":false,"gender":0,"id":1132439,"known_for_department":"Sound","name":"Terdsak Janpan","original_name":"Terdsak Janpan","popularity":0.149199999999999999289457264239899814128875732421875,"profile_path":"\/4vRYMjpRpWK9bPk2qeGIaix417s.jpg","credit_id":"6538288e94631800c6b5e7cf","department":"Sound","job":"Original Music Composer"},{"adult":false,"gender":0,"id":3682504,"known_for_department":"Production","name":"Vichaya Poolvaraluk","original_name":"Vichaya Poolvaraluk","popularity":0.02860000000000000042188474935755948536098003387451171875,"profile_path":null,"credit_id":"653be852719aeb011b979840","department":"Production","job":"Executive Producer"},{"adult":false,"gender":0,"id":1204806,"known_for_department":"Production","name":"Narint Yuvaboon","original_name":"Narint Yuvaboon","popularity":0.07249999999999999500399638918679556809365749359130859375,"profile_path":null,"credit_id":"653be869cc968300ea704e06","department":"Production","job":"Producer"},{"adult":false,"gender":0,"id":4342859,"known_for_department":"Writing","name":"Sorarat Jirabovornwisut","original_name":"Sorarat Jirabovornwisut","popularity":0.06690000000000000113242748511765967123210430145263671875,"profile_path":null,"credit_id":"653be948109cd0012cfe7d88","department":"Writing","job":"Screenplay"},{"adult":false,"gender":0,"id":1653729,"known_for_department":"Directing","name":"Kanchanaphan Meesuwan","original_name":"Kanchanaphan Meesuwan","popularity":0.0213999999999999988842258602517176768742501735687255859375,"profile_path":null,"credit_id":"6618f555bbcae0017c957cb2","department":"Production","job":"Producer"},{"adult":false,"gender":0,"id":3682503,"known_for_department":"Production","name":"Visarut Poolvaraluk","original_name":"Visarut Poolvaraluk","popularity":0.0441000000000000003108624468950438313186168670654296875,"profile_path":null,"credit_id":"6618f59ce10f46017db54d8b","department":"Production","job":"Executive Producer"},{"adult":false,"gender":0,"id":3005064,"known_for_department":"Production","name":"Surachedh Assawaruenganun","original_name":"Surachedh Assawaruenganun","popularity":0.040399999999999998412381074786026147194206714630126953125,"profile_path":null,"credit_id":"6618f5bb3acd20017c46cdcd","department":"Production","job":"Executive Producer"},{"adult":false,"gender":1,"id":4648891,"known_for_department":"Production","name":"Pinkamol Maleenont","original_name":"Pinkamol Maleenont","popularity":0.0914999999999999980015985556747182272374629974365234375,"profile_path":null,"credit_id":"6618f5f93acd20013045f574","department":"Production","job":"Executive Producer"},{"adult":false,"gender":0,"id":4648892,"known_for_department":"Production","name":"Tracy Ann Maleenont","original_name":"Tracy Ann Maleenont","popularity":0.0239000000000000011046719095020307577215135097503662109375,"profile_path":null,"credit_id":"6618f61fbbcae0017c957d99","department":"Production","job":"Executive Producer"},{"adult":false,"gender":0,"id":4648893,"known_for_department":"Production","name":"Surin Krittayaphongphun","original_name":"Surin Krittayaphongphun","popularity":0.04019999999999999962252417162744677625596523284912109375,"profile_path":null,"credit_id":"6618f63a90cf51017ca22111","department":"Production","job":"Executive Producer"},{"adult":false,"gender":0,"id":4648894,"known_for_department":"Writing","name":"Thammanan Chulaborirak","original_name":"Thammanan Chulaborirak","popularity":0.06690000000000000113242748511765967123210430145263671875,"profile_path":null,"credit_id":"6618f69b4da3d4017c9215e1","department":"Writing","job":"Screenplay"},{"adult":false,"gender":0,"id":4648896,"known_for_department":"Writing","name":"Krittanont","original_name":"Krittanont","popularity":0.0713000000000000022648549702353193424642086029052734375,"profile_path":null,"credit_id":"6618f6dcf9aa47017d346835","department":"Writing","job":"Story"},{"adult":false,"gender":0,"id":2270383,"known_for_department":"Art","name":"Sudkatd Luancharoen","original_name":"Sudkatd Luancharoen","popularity":0.048599999999999997368771431638378999195992946624755859375,"profile_path":null,"credit_id":"6618f70faf3da6017c18ce6b","department":"Production","job":"Production Designer"},{"adult":false,"gender":0,"id":1950247,"known_for_department":"Costume & Make-Up","name":"Praoplern Tangmitcharoen","original_name":"Praoplern Tangmitcharoen","popularity":0.07449999999999999678035322858704603277146816253662109375,"profile_path":null,"credit_id":"6618f749ea84c7017d56d1ae","department":"Costume & Make-Up","job":"Costume Designer"},{"adult":false,"gender":2,"id":2860343,"known_for_department":"Camera","name":"\u0e28\u0e23\u0e31\u0e13\u0e22\u0e4c \u0e28\u0e23\u0e35\u0e2a\u0e34\u0e07\u0e2b\u0e4c\u0e0a\u0e31\u0e22","original_name":"\u0e28\u0e23\u0e31\u0e13\u0e22\u0e4c \u0e28\u0e23\u0e35\u0e2a\u0e34\u0e07\u0e2b\u0e4c\u0e0a\u0e31\u0e22","popularity":0.1552000000000000046185277824406512081623077392578125,"profile_path":null,"credit_id":"6618f7802b21080164b9df62","department":"Camera","job":"Director of Photography"},{"adult":false,"gender":2,"id":3401220,"known_for_department":"Editing","name":"Saravuth Nakajad","original_name":"Saravuth Nakajad","popularity":0.042900000000000000632827124036339228041470050811767578125,"profile_path":null,"credit_id":"6618f812dd731b017e0abde9","department":"Editing","job":"Editor"},{"adult":false,"gender":0,"id":2339672,"known_for_department":"Directing","name":"Thanadet Pradit","original_name":"Thanadet Pradit","popularity":0.042900000000000000632827124036339228041470050811767578125,"profile_path":null,"credit_id":"6618f901af3da60149181dcb","department":"Directing","job":"First Assistant Director"},{"adult":false,"gender":2,"id":1665494,"known_for_department":"Editing","name":"Jirasak Chakkrawarn","original_name":"Jirasak Chakkrawarn","popularity":0.04120000000000000051070259132757200859487056732177734375,"profile_path":null,"credit_id":"6618f927f9aa47017d346a3c","department":"Directing","job":"Second Assistant Director"},{"adult":false,"gender":0,"id":3627600,"known_for_department":"Costume & Make-Up","name":"Manit Tansila","original_name":"Manit Tansila","popularity":0.080600000000000004973799150320701301097869873046875,"profile_path":null,"credit_id":"6618f9ede4c9eb01632a6bff","department":"Costume & Make-Up","job":"Hairstylist"},{"adult":false,"gender":0,"id":2294866,"known_for_department":"Costume & Make-Up","name":"Norrapat Muandech","original_name":"Norrapat Muandech","popularity":0.0213999999999999988842258602517176768742501735687255859375,"profile_path":null,"credit_id":"6618fa18ea84c70164565898","department":"Costume & Make-Up","job":"Hairstylist"},{"adult":false,"gender":0,"id":4648901,"known_for_department":"Costume & Make-Up","name":"Pattanapongkrit Kusumannukul","original_name":"Pattanapongkrit Kusumannukul","popularity":0.053600000000000001809663530139005160890519618988037109375,"profile_path":null,"credit_id":"6618fa6aea84c701645658f3","department":"Costume & Make-Up","job":"Hairstylist"},{"adult":false,"gender":0,"id":3596207,"known_for_department":"Costume & Make-Up","name":"Aummarit Chokpreecha","original_name":"Aummarit Chokpreecha","popularity":0.11100000000000000144328993201270350255072116851806640625,"profile_path":null,"credit_id":"6618fa7f109cd00165a38587","department":"Costume & Make-Up","job":"Makeup Artist"},{"adult":false,"gender":0,"id":4648903,"known_for_department":"Costume & Make-Up","name":"Patcharee Krongmalai","original_name":"Patcharee Krongmalai","popularity":0.014300000000000000210942374678779742680490016937255859375,"profile_path":null,"credit_id":"6618faaf3acd20017c46d341","department":"Costume & Make-Up","job":"Makeup Artist"},{"adult":false,"gender":0,"id":4006515,"known_for_department":"Costume & Make-Up","name":"Supachai Koonsiri","original_name":"Supachai Koonsiri","popularity":0.0213999999999999988842258602517176768742501735687255859375,"profile_path":null,"credit_id":"6618fabedd731b017e0ac06d","department":"Costume & Make-Up","job":"Makeup Artist"},{"adult":false,"gender":0,"id":1094685,"known_for_department":"Costume & Make-Up","name":"Jirawat Tasai","original_name":"Jirawat Tasai","popularity":0.1171999999999999986233234494648058898746967315673828125,"profile_path":null,"credit_id":"6618fad3e4c9eb017c2adb2a","department":"Costume & Make-Up","job":"Makeup Artist"},{"adult":false,"gender":0,"id":4648905,"known_for_department":"Costume & Make-Up","name":"Aimi Islam","original_name":"Aimi Islam","popularity":0.0213999999999999988842258602517176768742501735687255859375,"profile_path":null,"credit_id":"6618fb1cf9aa47017d346c00","department":"Costume & Make-Up","job":"Special Effects Makeup Artist"},{"adult":false,"gender":0,"id":1665658,"known_for_department":"Costume & Make-Up","name":"Sivakorn Suklungkarn","original_name":"Sivakorn Suklungkarn","popularity":0.08980000000000000481836792687317938543856143951416015625,"profile_path":null,"credit_id":"6618fb30e10f46017db55287","department":"Costume & Make-Up","job":"Special Effects Makeup Artist"},{"adult":false,"gender":2,"id":1650849,"known_for_department":"Costume & Make-Up","name":"\u0e2d\u0e32\u0e20\u0e23\u0e13\u0e4c \u0e21\u0e35\u0e1a\u0e32\u0e07\u0e22\u0e32\u0e07","original_name":"\u0e2d\u0e32\u0e20\u0e23\u0e13\u0e4c \u0e21\u0e35\u0e1a\u0e32\u0e07\u0e22\u0e32\u0e07","popularity":0.232399999999999995470290059529361315071582794189453125,"profile_path":"\/2CzXittQDcSx3CMnjYP9RdeDBRZ.jpg","credit_id":"6618fb463acd200163466355","department":"Costume & Make-Up","job":"Special Effects Makeup Artist"},{"adult":false,"gender":0,"id":4648906,"known_for_department":"Costume & Make-Up","name":"Ruchira Chaiyabhat","original_name":"Ruchira Chaiyabhat","popularity":0.060900000000000002742250870824136654846370220184326171875,"profile_path":null,"credit_id":"6618fb75bbcae0016295018a","department":"Costume & Make-Up","job":"Special Effects Makeup Artist"},{"adult":false,"gender":0,"id":4566097,"known_for_department":"Costume & Make-Up","name":"Mena Chongpaiboon","original_name":"Mena Chongpaiboon","popularity":0.0167999999999999989619414719754786347039043903350830078125,"profile_path":null,"credit_id":"6618fb88e10f46017db552c8","department":"Costume & Make-Up","job":"Special Effects Makeup Artist"},{"adult":false,"gender":0,"id":1067268,"known_for_department":"Sound","name":"Chakhrit Boriboon","original_name":"Chakhrit Boriboon","popularity":0.061699999999999997901678483458454138599336147308349609375,"profile_path":null,"credit_id":"6618fbbd4da3d4017c921b32","department":"Sound","job":"Sound Recordist"},{"adult":false,"gender":2,"id":64355,"known_for_department":"Sound","name":"\u0e44\u0e15\u0e23\u0e40\u0e17\u0e1e \u0e27\u0e07\u0e28\u0e4c\u0e44\u0e1e\u0e1a\u0e39\u0e25\u0e22\u0e4c","original_name":"\u0e44\u0e15\u0e23\u0e40\u0e17\u0e1e \u0e27\u0e07\u0e28\u0e4c\u0e44\u0e1e\u0e1a\u0e39\u0e25\u0e22\u0e4c","popularity":0.8451999999999999513278226004331372678279876708984375,"profile_path":"\/spP5idDWZ9NaUzZXhsPFBIgbw6a.jpg","credit_id":"6618fc48af3da60163186ed2","department":"Sound","job":"Sound Post Supervisor"}]}}